pomo.py
py_pomo-1.0.dist-info/LICENSE
py_pomo-1.0.dist-info/METADATA
py_pomo-1.0.dist-info/WHEEL
py_pomo-1.0.dist-info/entry_points.txt
py_pomo-1.0.dist-info/top_level.txt
py_pomo-1.0.dist-info/RECORD
