Metadata-Version: 2.1
Name: py-pomo
Version: 1.0
Summary: A simple CLI pomodoro timer
Home-page: https://github.com/BasicPixel/py-pomo
Author: Osama AlQudah
Author-email: osama.mo.qudah@gmail.com
License: MIT
Keywords: pomodoro,click,cli
Platform: UNKNOWN
Classifier: License :: OSI Approved :: MIT License
Classifier: Development Status :: 4 - Beta
Classifier: Environment :: Console
Classifier: Topic :: Utilities
License-File: LICENSE
Requires-Dist: Click
